LICENCE.md
MANIFEST.in
README.md
TODO.md
setup.py
yalr/__init__.py
yalr/grammar.py
yalr/lexer.py
yalr/lr.py
yalr/lr1.py
yalr/operations.py
yalr/slr.py
yalr.egg-info/PKG-INFO
yalr.egg-info/SOURCES.txt
yalr.egg-info/dependency_links.txt
yalr.egg-info/requires.txt
yalr.egg-info/top_level.txt