Metadata-Version: 1.1
Name: yalr
Version: 0.0.5
Summary: Yet Another LR(1) implementation
Home-page: https://github.com/jan-grant/python-yalr
Author: jan grant
Author-email: jang@ioctl.org
License: Copyright 2016 Jan Grant (jang@ioctl.org)
